socialdataanalysis/__init__.py
socialdataanalysis/association.py
socialdataanalysis/exploratoryfactoranalysis.py
socialdataanalysis-0.9.21.data/data/share/socialdataanalysis/Cap2_Ex10_Universidades&Tempo_estudo_exame.ipynb
socialdataanalysis-0.9.21.data/data/share/socialdataanalysis/Cap2_Ex11_Medicacao&Sexo Continente.ipynb
socialdataanalysis-0.9.21.data/data/share/socialdataanalysis/Cap2_Ex12_Bronquite&Exposicao Idade.ipynb
socialdataanalysis-0.9.21.data/data/share/socialdataanalysis/Cap2_Ex13_Autonomia&Satisfacao_por_Religiao.ipynb
socialdataanalysis-0.9.21.data/data/share/socialdataanalysis/Cap2_Ex14_Hemisferio&Tumor_por_Sitio.ipynb
socialdataanalysis-0.9.21.data/data/share/socialdataanalysis/Cap2_Ex15_Cinto&Ferimentos_por_Localizacao_e_Sexo.ipynb
socialdataanalysis-0.9.21.data/data/share/socialdataanalysis/Cap2_Ex16 SCA_Imagem_Pão Zona.ipynb
socialdataanalysis-0.9.21.data/data/share/socialdataanalysis/Cap2_Ex17 SCA_Prémio_Nobel_Países_Anos.ipynb
socialdataanalysis-0.9.21.data/data/share/socialdataanalysis/Cap2_Ex1_Aborto.ipynb
socialdataanalysis-0.9.21.data/data/share/socialdataanalysis/Cap2_Ex2_Rua&HIV.ipynb
socialdataanalysis-0.9.21.data/data/share/socialdataanalysis/Cap2_Ex3_Bebidas&Feridos.ipynb
socialdataanalysis-0.9.21.data/data/share/socialdataanalysis/Cap2_Ex4_Sexo&Comportamento.ipynb
socialdataanalysis-0.9.21.data/data/share/socialdataanalysis/Cap2_Ex5_Sexo&Compra.ipynb
socialdataanalysis-0.9.21.data/data/share/socialdataanalysis/Cap2_Ex6_Qualidade_de_um_Teste.ipynb
socialdataanalysis-0.9.21.data/data/share/socialdataanalysis/Cap2_Ex7_Qualidade_entre_dois_Testes.ipynb
socialdataanalysis-0.9.21.data/data/share/socialdataanalysis/Cap2_Ex8_Desempenho_modelo_classificacao_pecas.ipynb
socialdataanalysis-0.9.21.data/data/share/socialdataanalysis/Cap2_Ex9_Votos&Atitudes.ipynb
socialdataanalysis-0.9.21.data/data/share/socialdataanalysis/Cap4_Ex1_Uniformização_de_escalas.ipynb
socialdataanalysis-0.9.21.dist-info/LICENSE
socialdataanalysis-0.9.21.dist-info/METADATA
socialdataanalysis-0.9.21.dist-info/WHEEL
socialdataanalysis-0.9.21.dist-info/top_level.txt
socialdataanalysis-0.9.21.dist-info/RECORD
