Metadata-Version: 2.1
Name: socialdataanalysis
Version: 0.9.21
Summary: Funções personalizadas para análise de dados nas ciências sociais, complementando o uso do SPSS.
Home-page: https://github.com/rcmergulhao/socialdataanalysis
Author: Ricardo Mergulhao
Author-email: ricardomergulhao@gmail.com
Classifier: Programming Language :: Python :: 3
Classifier: License :: OSI Approved :: MIT License
Classifier: Operating System :: OS Independent
Requires-Python: >=3.6
License-File: LICENSE
Requires-Dist: pandas
Requires-Dist: numpy
Requires-Dist: statsmodels
Requires-Dist: scipy
Requires-Dist: matplotlib
Requires-Dist: sympy
Requires-Dist: prince
Requires-Dist: altair
Requires-Dist: pyreadstat
Requires-Dist: pingouin
